MANIFEST.in
README.md
setup.py
pygeoexif/__init__.py
pygeoexif/get.py
pygeoexif.egg-info/PKG-INFO
pygeoexif.egg-info/SOURCES.txt
pygeoexif.egg-info/dependency_links.txt
pygeoexif.egg-info/not-zip-safe
pygeoexif.egg-info/top_level.txt