Metadata-Version: 1.1
Name: pygeoexif
Version: 0.0.1
Summary: Simply get latitude and longitude from an image's EXIF data
Home-page: http://github.com/ebrelsford/pygeoexif
Author: Eric Brelsford
Author-email: ebrelsford@gmail.com
License: MIT License
Platform: UNKNOWN
Classifier: Development Status :: 4 - Beta
Classifier: Intended Audience :: Developers
Classifier: License :: OSI Approved :: MIT License
Classifier: Operating System :: OS Independent
Classifier: Programming Language :: Python
Classifier: Programming Language :: Python :: 2
Classifier: Programming Language :: Python :: 3
Classifier: Topic :: Multimedia :: Graphics
Classifier: Topic :: Scientific/Engineering :: GIS
Classifier: Topic :: Software Development
